loomr-0.1.6.dist-info/licenses/LICENSE
loomr-0.1.6.dist-info/licenses/NOTICE
messaging_service/__init__.py
messaging_service/api_server.py
messaging_service/cli.py
messaging_service/main.py
messaging_service/adapters/__init__.py
messaging_service/adapters/telegram/__init__.py
messaging_service/adapters/telegram/adapter.py
messaging_service/config/config.yaml
messaging_service/config/questionary.md
messaging_service/config/flows/onboarding.yaml
messaging_service/core/__init__.py
messaging_service/core/analytics.py
messaging_service/core/event_bus.py
messaging_service/core/group_meter.py
messaging_service/core/message.py
messaging_service/core/seller_store.py
messaging_service/core/service.py
messaging_service/core/user_store.py
messaging_service/plugins/__init__.py
messaging_service/plugins/admin_tools.py
messaging_service/plugins/analytics.py
messaging_service/plugins/crypto_watcher.py
messaging_service/plugins/dashboard.py
messaging_service/plugins/echo_handler.py
messaging_service/plugins/file_router.py
messaging_service/plugins/group_activation.py
messaging_service/plugins/invites.py
messaging_service/plugins/job_board.py
messaging_service/plugins/location_demo.py
messaging_service/plugins/menu.py
messaging_service/plugins/ollama_assistant.py
messaging_service/plugins/product_catalog.py
messaging_service/plugins/questionnaire_handler.py
messaging_service/plugins/start_router.py
messaging_service/plugins/support.py
messaging_service/plugins/ticker.py
messaging_service/plugins/ton_watcher.py
loomr-0.1.6.dist-info/METADATA
loomr-0.1.6.dist-info/WHEEL
loomr-0.1.6.dist-info/entry_points.txt
loomr-0.1.6.dist-info/top_level.txt
loomr-0.1.6.dist-info/RECORD
