Metadata-Version: 2.4
Name: Loomr
Version: 0.1.6
Summary: Modular, event-driven messaging bot runtime with plugins, YAML flows, and built-in FastAPI.
Author-email: Kai Gartner <hello@example.com>
License: Prosperity Public License 3.0.0 (non-commercial)
Project-URL: Homepage, https://github.com/ThePhotoCodeGrapher/Loomr
Project-URL: Documentation, https://github.com/ThePhotoCodeGrapher/Loomr#readme
Project-URL: Issues, https://github.com/ThePhotoCodeGrapher/Loomr/issues
Project-URL: Support, https://t.me/+i1RDBKJv0U01OTQ0
Keywords: telegram,bot,fastapi,plugins,event-bus,yaml,sdk
Classifier: Programming Language :: Python :: 3
Classifier: Programming Language :: Python :: 3.10
Classifier: Programming Language :: Python :: 3.11
Classifier: License :: Other/Proprietary License
Classifier: Intended Audience :: Developers
Classifier: Topic :: Software Development :: Libraries :: Application Frameworks
Requires-Python: >=3.10
License-File: LICENSE
License-File: NOTICE
Requires-Dist: aiogram<4,>=3.6
Requires-Dist: aiohttp>=3.9.1
Requires-Dist: PyYAML>=6.0.1
Requires-Dist: fastapi>=0.110.0
Requires-Dist: uvicorn>=0.29.0
Requires-Dist: aiosqlite>=0.19.0
Requires-Dist: pydantic>=2.6.4
Requires-Dist: typer>=0.12.0
Requires-Dist: rich>=13.7.0
Requires-Dist: paho-mqtt>=1.6.1
Requires-Dist: cairosvg>=2.7.1
Requires-Dist: Pillow>=10.2.0
Dynamic: license-file
